[{"_id":"6798bfe5aa79035a3fa508b4","duration":42,"activityType":"gaming","userId":"1","activityTime":"all day","isHabit":false,"date":"2025-01-25T00:00:00.000Z","__v":0,"createdAt":"2025-01-28T11:30:45.103Z","updatedAt":"2025-01-28T11:30:45.103Z"},{"_id":"6798bfe5aa79035a3fa508b5","duration":145,"activityType":"screen time","userId":"1","activityTime":"all day","isHabit":false,"date":"2024-12-28T00:00:00.000Z","__v":0,"createdAt":"2025-01-28T11:30:45.104Z","updatedAt":"2025-01-28T11:30:45.104Z"},{"_id":"6798bfe5aa79035a3fa508b6","duration":68,"activityType":"friends","userId":"1","activityTime":"all day","isHabit":false,"date":"2024-12-28T00:00:00.000Z","__v":0,"createdAt":"2025-01-28T11:30:45.104Z","updatedAt":"2025-01-28T11:30:45.104Z"},{"_id":"6798bfe5aa79035a3fa508b7","duration":176,"activityType":"meditation","userId":"1","activityTime":"all day","isHabit":false,"date":"2024-11-25T00:00:00.000Z","__v":0,"createdAt":"2025-01-28T11:30:45.104Z","updatedAt":"2025-01-28T11:30:45.104Z"},{"_id":"6798bfe5aa79035a3fa508b8","duration":157,"activityType":"overtime","userId":"1","activityTime":"all day","isHabit":false,"date":"2024-12-02T00:00:00.000Z","__v":0,"createdAt":"2025-01-28T11:30:45.104Z","updatedAt":"2025-01-28T11:30:45.104Z"},{"_id":"6798bfe5aa79035a3fa508b9","duration":153,"activityType":"smoking","userId":"1","activityTime":"morning","isHabit":false,"date":"2025-01-07T00:00:00.000Z","__v":0,"createdAt":"2025-01-28T11:30:45.104Z","updatedAt":"2025-01-28T11:30:45.104Z"},{"_id":"6798bfe5aa79035a3fa508ba","duration":141,"activityType":"smoking","userId":"1","activityTime":"morning","isHabit":false,"date":"2024-12-17T00:00:00.000Z","__v":0,"createdAt":"2025-01-28T11:30:45.104Z","updatedAt":"2025-01-28T11:30:45.104Z"},{"_id":"6798bfe5aa79035a3fa508bb","duration":34,"activityType":"fast food","userId":"1","activityTime":"afternoon","isHabit":false,"date":"2024-11-14T00:00:00.000Z","__v":0,"createdAt":"2025-01-28T11:30:45.104Z","updatedAt":"2025-01-28T11:30:45.104Z"},{"_id":"6798bfe5aa79035a3fa508bc","duration":106,"activityType":"meditation","userId":"1","activityTime":"all day","isHabit":false,"date":"2024-12-31T00:00:00.000Z","__v":0,"createdAt":"2025-01-28T11:30:45.104Z","updatedAt":"2025-01-28T11:30:45.104Z"},{"_id":"6798bfe5aa79035a3fa508bd","duration":14,"activityType":"overtime","userId":"1","activityTime":"all day","isHabit":false,"date":"2024-12-13T00:00:00.000Z","__v":0,"createdAt":"2025-01-28T11:30:45.104Z","updatedAt":"2025-01-28T11:30:45.104Z"},{"_id":"6798bfe5aa79035a3fa508be","duration":38,"activityType":"party","userId":"1","activityTime":"evening","isHabit":false,"date":"2025-01-23T00:00:00.000Z","__v":0,"createdAt":"2025-01-28T11:30:45.104Z","updatedAt":"2025-01-28T11:30:45.104Z"},{"_id":"6798bfe5aa79035a3fa508bf","duration":134,"activityType":"cooking","userId":"1","activityTime":"morning","isHabit":false,"date":"2025-01-10T00:00:00.000Z","__v":0,"createdAt":"2025-01-28T11:30:45.104Z","updatedAt":"2025-01-28T11:30:45.104Z"},{"_id":"6798bfe5aa79035a3fa508c0","duration":45,"activityType":"cooking","userId":"1","activityTime":"all day","isHabit":false,"date":"2024-11-30T00:00:00.000Z","__v":0,"createdAt":"2025-01-28T11:30:45.104Z","updatedAt":"2025-01-28T11:30:45.104Z"},{"_id":"6798bfe5aa79035a3fa508c1","duration":16,"activityType":"meditation","userId":"1","activityTime":"afternoon","isHabit":false,"date":"2024-12-10T00:00:00.000Z","__v":0,"createdAt":"2025-01-28T11:30:45.104Z","updatedAt":"2025-01-28T11:30:45.104Z"},{"_id":"6798bfe5aa79035a3fa508c2","duration":67,"activityType":"fast food","userId":"1","activityTime":"evening","isHabit":false,"date":"2025-01-07T00:00:00.000Z","__v":0,"createdAt":"2025-01-28T11:30:45.104Z","updatedAt":"2025-01-28T11:30:45.104Z"},{"_id":"6798bfe5aa79035a3fa508c3","duration":73,"activityType":"overtime","userId":"1","activityTime":"afternoon","isHabit":false,"date":"2024-12-16T00:00:00.000Z","__v":0,"createdAt":"2025-01-28T11:30:45.104Z","updatedAt":"2025-01-28T11:30:45.104Z"},{"_id":"6798bfe5aa79035a3fa508c4","duration":118,"activityType":"cooking","userId":"1","activityTime":"afternoon","isHabit":false,"date":"2025-01-11T00:00:00.000Z","__v":0,"createdAt":"2025-01-28T11:30:45.104Z","updatedAt":"2025-01-28T11:30:45.104Z"},{"_id":"6798bfe5aa79035a3fa508c5","duration":29,"activityType":"exercise","userId":"1","activityTime":"evening","isHabit":false,"date":"2024-12-11T00:00:00.000Z","__v":0,"createdAt":"2025-01-28T11:30:45.104Z","updatedAt":"2025-01-28T11:30:45.104Z"},{"_id":"6798bfe5aa79035a3fa508c6","duration":131,"activityType":"cooking","userId":"1","activityTime":"morning","isHabit":false,"date":"2024-11-11T00:00:00.000Z","__v":0,"createdAt":"2025-01-28T11:30:45.104Z","updatedAt":"2025-01-28T11:30:45.104Z"},{"_id":"6798bfe5aa79035a3fa508c7","duration":73,"activityType":"cooking","userId":"1","activityTime":"all day","isHabit":false,"date":"2024-11-19T00:00:00.000Z","__v":0,"createdAt":"2025-01-28T11:30:45.105Z","updatedAt":"2025-01-28T11:30:45.105Z"},{"_id":"6798bfe5aa79035a3fa508c8","duration":88,"activityType":"meditation","userId":"1","activityTime":"morning","isHabit":false,"date":"2024-12-25T00:00:00.000Z","__v":0,"createdAt":"2025-01-28T11:30:45.105Z","updatedAt":"2025-01-28T11:30:45.105Z"},{"_id":"6798bfe5aa79035a3fa508c9","duration":66,"activityType":"fast food","userId":"1","activityTime":"morning","isHabit":false,"date":"2024-12-19T00:00:00.000Z","__v":0,"createdAt":"2025-01-28T11:30:45.105Z","updatedAt":"2025-01-28T11:30:45.105Z"},{"_id":"6798bfe5aa79035a3fa508ca","duration":55,"activityType":"fast food","userId":"1","activityTime":"morning","isHabit":false,"date":"2024-12-12T00:00:00.000Z","__v":0,"createdAt":"2025-01-28T11:30:45.105Z","updatedAt":"2025-01-28T11:30:45.105Z"},{"_id":"6798bfe5aa79035a3fa508cb","duration":22,"activityType":"party","userId":"1","activityTime":"all day","isHabit":false,"date":"2024-10-29T00:00:00.000Z","__v":0,"createdAt":"2025-01-28T11:30:45.105Z","updatedAt":"2025-01-28T11:30:45.105Z"},{"_id":"6798bfe5aa79035a3fa508cc","duration":133,"activityType":"exercise","userId":"1","activityTime":"morning","isHabit":false,"date":"2025-01-23T00:00:00.000Z","__v":0,"createdAt":"2025-01-28T11:30:45.105Z","updatedAt":"2025-01-28T11:30:45.105Z"},{"_id":"6798bfe5aa79035a3fa508cd","duration":73,"activityType":"cleaning","userId":"1","activityTime":"evening","isHabit":false,"date":"2024-12-24T00:00:00.000Z","__v":0,"createdAt":"2025-01-28T11:30:45.105Z","updatedAt":"2025-01-28T11:30:45.105Z"},{"_id":"6798bfe5aa79035a3fa508ce","duration":152,"activityType":"shopping","userId":"1","activityTime":"afternoon","isHabit":false,"date":"2024-12-03T00:00:00.000Z","__v":0,"createdAt":"2025-01-28T11:30:45.105Z","updatedAt":"2025-01-28T11:30:45.105Z"},{"_id":"6798bfe5aa79035a3fa508cf","duration":83,"activityType":"gaming","userId":"1","activityTime":"all day","isHabit":false,"date":"2024-11-03T00:00:00.000Z","__v":0,"createdAt":"2025-01-28T11:30:45.105Z","updatedAt":"2025-01-28T11:30:45.105Z"},{"_id":"6798bfe5aa79035a3fa508d0","duration":118,"activityType":"exercise","userId":"1","activityTime":"afternoon","isHabit":false,"date":"2024-10-31T00:00:00.000Z","__v":0,"createdAt":"2025-01-28T11:30:45.105Z","updatedAt":"2025-01-28T11:30:45.105Z"},{"_id":"6798bfe5aa79035a3fa508d1","duration":14,"activityType":"friends","userId":"1","activityTime":"morning","isHabit":false,"date":"2024-12-08T00:00:00.000Z","__v":0,"createdAt":"2025-01-28T11:30:45.105Z","updatedAt":"2025-01-28T11:30:45.105Z"},{"_id":"6798bfe5aa79035a3fa508d2","duration":73,"activityType":"shopping","userId":"1","activityTime":"morning","isHabit":false,"date":"2024-11-04T00:00:00.000Z","__v":0,"createdAt":"2025-01-28T11:30:45.105Z","updatedAt":"2025-01-28T11:30:45.105Z"},{"_id":"6798bfe5aa79035a3fa508d3","duration":142,"activityType":"party","userId":"1","activityTime":"morning","isHabit":false,"date":"2024-11-27T00:00:00.000Z","__v":0,"createdAt":"2025-01-28T11:30:45.105Z","updatedAt":"2025-01-28T11:30:45.105Z"},{"_id":"6798bfe5aa79035a3fa508d4","duration":105,"activityType":"smoking","userId":"1","activityTime":"all day","isHabit":false,"date":"2024-11-16T00:00:00.000Z","__v":0,"createdAt":"2025-01-28T11:30:45.105Z","updatedAt":"2025-01-28T11:30:45.105Z"},{"_id":"6798bfe5aa79035a3fa508d5","duration":140,"activityType":"cleaning","userId":"1","activityTime":"all day","isHabit":false,"date":"2024-11-25T00:00:00.000Z","__v":0,"createdAt":"2025-01-28T11:30:45.105Z","updatedAt":"2025-01-28T11:30:45.105Z"},{"_id":"6798bfe5aa79035a3fa508d6","duration":121,"activityType":"overtime","userId":"1","activityTime":"morning","isHabit":false,"date":"2024-12-02T00:00:00.000Z","__v":0,"createdAt":"2025-01-28T11:30:45.105Z","updatedAt":"2025-01-28T11:30:45.105Z"},{"_id":"6798bfe5aa79035a3fa508d7","duration":45,"activityType":"screen time","userId":"1","activityTime":"all day","isHabit":false,"date":"2024-11-27T00:00:00.000Z","__v":0,"createdAt":"2025-01-28T11:30:45.105Z","updatedAt":"2025-01-28T11:30:45.105Z"},{"_id":"6798bfe5aa79035a3fa508d8","duration":73,"activityType":"shopping","userId":"1","activityTime":"all day","isHabit":false,"date":"2025-01-18T00:00:00.000Z","__v":0,"createdAt":"2025-01-28T11:30:45.105Z","updatedAt":"2025-01-28T11:30:45.105Z"},{"_id":"6798bfe5aa79035a3fa508d9","duration":171,"activityType":"shopping","userId":"1","activityTime":"evening","isHabit":false,"date":"2025-01-14T00:00:00.000Z","__v":0,"createdAt":"2025-01-28T11:30:45.105Z","updatedAt":"2025-01-28T11:30:45.105Z"},{"_id":"6798bfe5aa79035a3fa508da","duration":82,"activityType":"exercise","userId":"1","activityTime":"morning","isHabit":false,"date":"2024-11-24T00:00:00.000Z","__v":0,"createdAt":"2025-01-28T11:30:45.105Z","updatedAt":"2025-01-28T11:30:45.105Z"},{"_id":"6798bfe5aa79035a3fa508db","duration":142,"activityType":"shopping","userId":"1","activityTime":"all day","isHabit":false,"date":"2024-12-16T00:00:00.000Z","__v":0,"createdAt":"2025-01-28T11:30:45.105Z","updatedAt":"2025-01-28T11:30:45.105Z"},{"_id":"6798bfe5aa79035a3fa508dc","duration":73,"activityType":"cooking","userId":"1","activityTime":"evening","isHabit":false,"date":"2024-11-29T00:00:00.000Z","__v":0,"createdAt":"2025-01-28T11:30:45.105Z","updatedAt":"2025-01-28T11:30:45.105Z"},{"_id":"6798bfe5aa79035a3fa508dd","duration":171,"activityType":"screen time","userId":"1","activityTime":"morning","isHabit":false,"date":"2024-12-02T00:00:00.000Z","__v":0,"createdAt":"2025-01-28T11:30:45.105Z","updatedAt":"2025-01-28T11:30:45.105Z"},{"_id":"6798bfe5aa79035a3fa508de","duration":104,"activityType":"overtime","userId":"1","activityTime":"evening","isHabit":false,"date":"2024-11-08T00:00:00.000Z","__v":0,"createdAt":"2025-01-28T11:30:45.105Z","updatedAt":"2025-01-28T11:30:45.105Z"},{"_id":"6798bfe5aa79035a3fa508df","duration":24,"activityType":"screen time","userId":"1","activityTime":"morning","isHabit":false,"date":"2024-12-21T00:00:00.000Z","__v":0,"createdAt":"2025-01-28T11:30:45.105Z","updatedAt":"2025-01-28T11:30:45.105Z"},{"_id":"6798bfe5aa79035a3fa508e0","duration":83,"activityType":"exercise","userId":"1","activityTime":"morning","isHabit":false,"date":"2024-10-29T00:00:00.000Z","__v":0,"createdAt":"2025-01-28T11:30:45.105Z","updatedAt":"2025-01-28T11:30:45.105Z"},{"_id":"6798bfe5aa79035a3fa508e1","duration":118,"activityType":"reading","userId":"1","activityTime":"morning","isHabit":false,"date":"2025-01-12T00:00:00.000Z","__v":0,"createdAt":"2025-01-28T11:30:45.105Z","updatedAt":"2025-01-28T11:30:45.105Z"},{"_id":"6798bfe5aa79035a3fa508e2","duration":133,"activityType":"fast food","userId":"1","activityTime":"morning","isHabit":false,"date":"2025-01-11T00:00:00.000Z","__v":0,"createdAt":"2025-01-28T11:30:45.105Z","updatedAt":"2025-01-28T11:30:45.105Z"},{"_id":"6798bfe5aa79035a3fa508e3","duration":130,"activityType":"meditation","userId":"1","activityTime":"all day","isHabit":false,"date":"2024-11-12T00:00:00.000Z","__v":0,"createdAt":"2025-01-28T11:30:45.105Z","updatedAt":"2025-01-28T11:30:45.105Z"},{"_id":"6798bfe5aa79035a3fa508e4","duration":39,"activityType":"smoking","userId":"1","activityTime":"morning","isHabit":false,"date":"2025-01-22T00:00:00.000Z","__v":0,"createdAt":"2025-01-28T11:30:45.105Z","updatedAt":"2025-01-28T11:30:45.105Z"},{"_id":"6798bfe5aa79035a3fa508e5","duration":166,"activityType":"party","userId":"1","activityTime":"evening","isHabit":false,"date":"2024-12-02T00:00:00.000Z","__v":0,"createdAt":"2025-01-28T11:30:45.105Z","updatedAt":"2025-01-28T11:30:45.105Z"},{"_id":"6798bfe5aa79035a3fa508e6","duration":55,"activityType":"cleaning","userId":"1","activityTime":"all day","isHabit":false,"date":"2024-11-29T00:00:00.000Z","__v":0,"createdAt":"2025-01-28T11:30:45.105Z","updatedAt":"2025-01-28T11:30:45.105Z"},{"_id":"6798bfe5aa79035a3fa508e7","duration":121,"activityType":"screen time","userId":"1","activityTime":"all day","isHabit":false,"date":"2024-12-14T00:00:00.000Z","__v":0,"createdAt":"2025-01-28T11:30:45.105Z","updatedAt":"2025-01-28T11:30:45.105Z"},{"_id":"6798bfe5aa79035a3fa508e8","duration":41,"activityType":"party","userId":"1","activityTime":"afternoon","isHabit":false,"date":"2024-11-10T00:00:00.000Z","__v":0,"createdAt":"2025-01-28T11:30:45.105Z","updatedAt":"2025-01-28T11:30:45.105Z"},{"_id":"6798bfe5aa79035a3fa508e9","duration":145,"activityType":"cooking","userId":"1","activityTime":"evening","isHabit":false,"date":"2024-12-20T00:00:00.000Z","__v":0,"createdAt":"2025-01-28T11:30:45.105Z","updatedAt":"2025-01-28T11:30:45.105Z"},{"_id":"6798bfe5aa79035a3fa508ea","duration":102,"activityType":"screen time","userId":"1","activityTime":"evening","isHabit":false,"date":"2024-11-19T00:00:00.000Z","__v":0,"createdAt":"2025-01-28T11:30:45.105Z","updatedAt":"2025-01-28T11:30:45.105Z"},{"_id":"6798bfe5aa79035a3fa508eb","duration":140,"activityType":"friends","userId":"1","activityTime":"afternoon","isHabit":false,"date":"2025-01-03T00:00:00.000Z","__v":0,"createdAt":"2025-01-28T11:30:45.105Z","updatedAt":"2025-01-28T11:30:45.105Z"},{"_id":"6798bfe5aa79035a3fa508ec","duration":108,"activityType":"shopping","userId":"1","activityTime":"evening","isHabit":false,"date":"2024-12-14T00:00:00.000Z","__v":0,"createdAt":"2025-01-28T11:30:45.105Z","updatedAt":"2025-01-28T11:30:45.105Z"},{"_id":"6798bfe5aa79035a3fa508ed","duration":160,"activityType":"cooking","userId":"1","activityTime":"morning","isHabit":false,"date":"2025-01-21T00:00:00.000Z","__v":0,"createdAt":"2025-01-28T11:30:45.105Z","updatedAt":"2025-01-28T11:30:45.105Z"},{"_id":"6798bfe5aa79035a3fa508ee","duration":52,"activityType":"reading","userId":"1","activityTime":"morning","isHabit":false,"date":"2024-12-26T00:00:00.000Z","__v":0,"createdAt":"2025-01-28T11:30:45.105Z","updatedAt":"2025-01-28T11:30:45.105Z"},{"_id":"6798bfe5aa79035a3fa508ef","duration":150,"activityType":"meditation","userId":"1","activityTime":"all day","isHabit":false,"date":"2024-11-27T00:00:00.000Z","__v":0,"createdAt":"2025-01-28T11:30:45.105Z","updatedAt":"2025-01-28T11:30:45.105Z"},{"_id":"6798bfe5aa79035a3fa508f0","duration":39,"activityType":"cleaning","userId":"1","activityTime":"all day","isHabit":false,"date":"2024-12-24T00:00:00.000Z","__v":0,"createdAt":"2025-01-28T11:30:45.105Z","updatedAt":"2025-01-28T11:30:45.105Z"},{"_id":"6798bfe5aa79035a3fa508f1","duration":22,"activityType":"screen time","userId":"1","activityTime":"evening","isHabit":false,"date":"2025-01-06T00:00:00.000Z","__v":0,"createdAt":"2025-01-28T11:30:45.105Z","updatedAt":"2025-01-28T11:30:45.105Z"},{"_id":"6798bfe5aa79035a3fa508f2","duration":125,"activityType":"shopping","userId":"1","activityTime":"morning","isHabit":false,"date":"2024-12-09T00:00:00.000Z","__v":0,"createdAt":"2025-01-28T11:30:45.105Z","updatedAt":"2025-01-28T11:30:45.105Z"},{"_id":"6798bfe5aa79035a3fa508f3","duration":99,"activityType":"overtime","userId":"1","activityTime":"afternoon","isHabit":false,"date":"2024-11-09T00:00:00.000Z","__v":0,"createdAt":"2025-01-28T11:30:45.105Z","updatedAt":"2025-01-28T11:30:45.105Z"},{"_id":"6798bfe5aa79035a3fa508f4","duration":174,"activityType":"exercise","userId":"1","activityTime":"evening","isHabit":false,"date":"2025-01-26T00:00:00.000Z","__v":0,"createdAt":"2025-01-28T11:30:45.105Z","updatedAt":"2025-01-28T11:30:45.105Z"},{"_id":"6798bfe5aa79035a3fa508f5","duration":56,"activityType":"cooking","userId":"1","activityTime":"afternoon","isHabit":false,"date":"2024-11-10T00:00:00.000Z","__v":0,"createdAt":"2025-01-28T11:30:45.105Z","updatedAt":"2025-01-28T11:30:45.105Z"},{"_id":"6798bfe5aa79035a3fa508f6","duration":15,"activityType":"gaming","userId":"1","activityTime":"morning","isHabit":false,"date":"2025-01-11T00:00:00.000Z","__v":0,"createdAt":"2025-01-28T11:30:45.105Z","updatedAt":"2025-01-28T11:30:45.105Z"},{"_id":"6798bfe5aa79035a3fa508f7","duration":60,"activityType":"friends","userId":"1","activityTime":"afternoon","isHabit":false,"date":"2024-11-08T00:00:00.000Z","__v":0,"createdAt":"2025-01-28T11:30:45.105Z","updatedAt":"2025-01-28T11:30:45.105Z"},{"_id":"6798bfe5aa79035a3fa508f8","duration":78,"activityType":"reading","userId":"1","activityTime":"morning","isHabit":false,"date":"2024-12-31T00:00:00.000Z","__v":0,"createdAt":"2025-01-28T11:30:45.105Z","updatedAt":"2025-01-28T11:30:45.105Z"},{"_id":"6798bfe5aa79035a3fa508f9","duration":38,"activityType":"cleaning","userId":"1","activityTime":"evening","isHabit":false,"date":"2025-01-15T00:00:00.000Z","__v":0,"createdAt":"2025-01-28T11:30:45.105Z","updatedAt":"2025-01-28T11:30:45.105Z"},{"_id":"6798bfe5aa79035a3fa508fa","duration":45,"activityType":"reading","userId":"1","activityTime":"all day","isHabit":false,"date":"2025-01-10T00:00:00.000Z","__v":0,"createdAt":"2025-01-28T11:30:45.105Z","updatedAt":"2025-01-28T11:30:45.105Z"},{"_id":"6798bfe5aa79035a3fa508fb","duration":28,"activityType":"exercise","userId":"1","activityTime":"evening","isHabit":false,"date":"2024-11-12T00:00:00.000Z","__v":0,"createdAt":"2025-01-28T11:30:45.105Z","updatedAt":"2025-01-28T11:30:45.105Z"},{"_id":"6798bfe5aa79035a3fa508fc","duration":118,"activityType":"friends","userId":"1","activityTime":"afternoon","isHabit":false,"date":"2025-01-04T00:00:00.000Z","__v":0,"createdAt":"2025-01-28T11:30:45.105Z","updatedAt":"2025-01-28T11:30:45.105Z"},{"_id":"6798bfe5aa79035a3fa508fd","duration":51,"activityType":"exercise","userId":"1","activityTime":"afternoon","isHabit":false,"date":"2025-01-11T00:00:00.000Z","__v":0,"createdAt":"2025-01-28T11:30:45.105Z","updatedAt":"2025-01-28T11:30:45.105Z"},{"_id":"6798bfe5aa79035a3fa508fe","duration":54,"activityType":"overtime","userId":"1","activityTime":"morning","isHabit":false,"date":"2025-01-16T00:00:00.000Z","__v":0,"createdAt":"2025-01-28T11:30:45.105Z","updatedAt":"2025-01-28T11:30:45.105Z"},{"_id":"6798bfe5aa79035a3fa508ff","duration":118,"activityType":"cleaning","userId":"1","activityTime":"afternoon","isHabit":false,"date":"2025-01-15T00:00:00.000Z","__v":0,"createdAt":"2025-01-28T11:30:45.105Z","updatedAt":"2025-01-28T11:30:45.105Z"},{"_id":"6798bfe5aa79035a3fa50900","duration":43,"activityType":"exercise","userId":"1","activityTime":"afternoon","isHabit":false,"date":"2024-11-28T00:00:00.000Z","__v":0,"createdAt":"2025-01-28T11:30:45.105Z","updatedAt":"2025-01-28T11:30:45.105Z"},{"_id":"6798bfe5aa79035a3fa50901","duration":168,"activityType":"party","userId":"1","activityTime":"evening","isHabit":false,"date":"2024-11-15T00:00:00.000Z","__v":0,"createdAt":"2025-01-28T11:30:45.105Z","updatedAt":"2025-01-28T11:30:45.105Z"},{"_id":"6798bfe5aa79035a3fa50902","duration":79,"activityType":"smoking","userId":"1","activityTime":"morning","isHabit":false,"date":"2025-01-03T00:00:00.000Z","__v":0,"createdAt":"2025-01-28T11:30:45.105Z","updatedAt":"2025-01-28T11:30:45.105Z"},{"_id":"6798bfe5aa79035a3fa50903","duration":133,"activityType":"reading","userId":"1","activityTime":"morning","isHabit":false,"date":"2024-12-06T00:00:00.000Z","__v":0,"createdAt":"2025-01-28T11:30:45.105Z","updatedAt":"2025-01-28T11:30:45.105Z"},{"_id":"6798bfe5aa79035a3fa50904","duration":52,"activityType":"screen time","userId":"1","activityTime":"morning","isHabit":false,"date":"2025-01-12T00:00:00.000Z","__v":0,"createdAt":"2025-01-28T11:30:45.105Z","updatedAt":"2025-01-28T11:30:45.105Z"},{"_id":"6798bfe5aa79035a3fa50905","duration":61,"activityType":"screen time","userId":"1","activityTime":"morning","isHabit":false,"date":"2025-01-21T00:00:00.000Z","__v":0,"createdAt":"2025-01-28T11:30:45.105Z","updatedAt":"2025-01-28T11:30:45.105Z"},{"_id":"6798bfe5aa79035a3fa50906","duration":135,"activityType":"smoking","userId":"1","activityTime":"afternoon","isHabit":false,"date":"2024-12-03T00:00:00.000Z","__v":0,"createdAt":"2025-01-28T11:30:45.105Z","updatedAt":"2025-01-28T11:30:45.105Z"},{"_id":"6798bfe5aa79035a3fa50907","duration":177,"activityType":"friends","userId":"1","activityTime":"afternoon","isHabit":false,"date":"2025-01-18T00:00:00.000Z","__v":0,"createdAt":"2025-01-28T11:30:45.105Z","updatedAt":"2025-01-28T11:30:45.105Z"},{"_id":"6798bfe5aa79035a3fa50908","duration":177,"activityType":"friends","userId":"1","activityTime":"afternoon","isHabit":false,"date":"2024-11-19T00:00:00.000Z","__v":0,"createdAt":"2025-01-28T11:30:45.105Z","updatedAt":"2025-01-28T11:30:45.105Z"},{"_id":"6798bfe5aa79035a3fa50909","duration":161,"activityType":"friends","userId":"1","activityTime":"afternoon","isHabit":false,"date":"2025-01-14T00:00:00.000Z","__v":0,"createdAt":"2025-01-28T11:30:45.105Z","updatedAt":"2025-01-28T11:30:45.105Z"},{"_id":"6798bfe5aa79035a3fa5090a","duration":172,"activityType":"reading","userId":"1","activityTime":"afternoon","isHabit":false,"date":"2025-01-13T00:00:00.000Z","__v":0,"createdAt":"2025-01-28T11:30:45.105Z","updatedAt":"2025-01-28T11:30:45.105Z"},{"_id":"6798bfe5aa79035a3fa5090b","duration":13,"activityType":"party","userId":"1","activityTime":"morning","isHabit":false,"date":"2024-12-31T00:00:00.000Z","__v":0,"createdAt":"2025-01-28T11:30:45.105Z","updatedAt":"2025-01-28T11:30:45.105Z"},{"_id":"6798bfe5aa79035a3fa5090c","duration":78,"activityType":"smoking","userId":"1","activityTime":"all day","isHabit":false,"date":"2024-12-09T00:00:00.000Z","__v":0,"createdAt":"2025-01-28T11:30:45.105Z","updatedAt":"2025-01-28T11:30:45.105Z"},{"_id":"6798bfe5aa79035a3fa5090d","duration":53,"activityType":"gaming","userId":"1","activityTime":"afternoon","isHabit":false,"date":"2024-12-09T00:00:00.000Z","__v":0,"createdAt":"2025-01-28T11:30:45.105Z","updatedAt":"2025-01-28T11:30:45.105Z"},{"_id":"6798bfe5aa79035a3fa5090e","duration":108,"activityType":"fast food","userId":"1","activityTime":"afternoon","isHabit":false,"date":"2025-01-27T00:00:00.000Z","__v":0,"createdAt":"2025-01-28T11:30:45.105Z","updatedAt":"2025-01-28T11:30:45.105Z"},{"_id":"6798bfe5aa79035a3fa5090f","duration":68,"activityType":"friends","userId":"1","activityTime":"afternoon","isHabit":false,"date":"2024-11-07T00:00:00.000Z","__v":0,"createdAt":"2025-01-28T11:30:45.105Z","updatedAt":"2025-01-28T11:30:45.105Z"},{"_id":"6798bfe5aa79035a3fa50910","duration":21,"activityType":"reading","userId":"1","activityTime":"evening","isHabit":false,"date":"2024-12-07T00:00:00.000Z","__v":0,"createdAt":"2025-01-28T11:30:45.105Z","updatedAt":"2025-01-28T11:30:45.105Z"},{"_id":"6798bfe5aa79035a3fa50911","duration":154,"activityType":"party","userId":"1","activityTime":"evening","isHabit":false,"date":"2024-12-02T00:00:00.000Z","__v":0,"createdAt":"2025-01-28T11:30:45.105Z","updatedAt":"2025-01-28T11:30:45.105Z"},{"_id":"6798bfe5aa79035a3fa50912","duration":123,"activityType":"cleaning","userId":"1","activityTime":"morning","isHabit":false,"date":"2024-12-28T00:00:00.000Z","__v":0,"createdAt":"2025-01-28T11:30:45.105Z","updatedAt":"2025-01-28T11:30:45.105Z"},{"_id":"6798bfe5aa79035a3fa50913","duration":122,"activityType":"gaming","userId":"1","activityTime":"afternoon","isHabit":false,"date":"2024-11-27T00:00:00.000Z","__v":0,"createdAt":"2025-01-28T11:30:45.105Z","updatedAt":"2025-01-28T11:30:45.105Z"},{"_id":"6798bfe5aa79035a3fa50914","duration":150,"activityType":"cleaning","userId":"1","activityTime":"evening","isHabit":false,"date":"2024-11-15T00:00:00.000Z","__v":0,"createdAt":"2025-01-28T11:30:45.105Z","updatedAt":"2025-01-28T11:30:45.105Z"},{"_id":"6798bfe5aa79035a3fa50915","duration":77,"activityType":"exercise","userId":"1","activityTime":"evening","isHabit":false,"date":"2024-12-05T00:00:00.000Z","__v":0,"createdAt":"2025-01-28T11:30:45.105Z","updatedAt":"2025-01-28T11:30:45.105Z"},{"_id":"6798bfe5aa79035a3fa50916","duration":171,"activityType":"smoking","userId":"1","activityTime":"afternoon","isHabit":false,"date":"2024-11-25T00:00:00.000Z","__v":0,"createdAt":"2025-01-28T11:30:45.105Z","updatedAt":"2025-01-28T11:30:45.105Z"},{"_id":"6798bfe5aa79035a3fa50917","duration":141,"activityType":"exercise","userId":"1","activityTime":"morning","isHabit":false,"date":"2024-11-21T00:00:00.000Z","__v":0,"createdAt":"2025-01-28T11:30:45.105Z","updatedAt":"2025-01-28T11:30:45.105Z"},{"_id":"6798bfe5aa79035a3fa50918","duration":31,"activityType":"cleaning","userId":"1","activityTime":"afternoon","isHabit":false,"date":"2024-11-27T00:00:00.000Z","__v":0,"createdAt":"2025-01-28T11:30:45.105Z","updatedAt":"2025-01-28T11:30:45.105Z"},{"_id":"6798bfe5aa79035a3fa50919","duration":132,"activityType":"smoking","userId":"1","activityTime":"evening","isHabit":false,"date":"2025-01-09T00:00:00.000Z","__v":0,"createdAt":"2025-01-28T11:30:45.105Z","updatedAt":"2025-01-28T11:30:45.105Z"},{"_id":"6798bfe5aa79035a3fa5091a","duration":157,"activityType":"overtime","userId":"1","activityTime":"all day","isHabit":false,"date":"2024-12-16T00:00:00.000Z","__v":0,"createdAt":"2025-01-28T11:30:45.105Z","updatedAt":"2025-01-28T11:30:45.105Z"},{"_id":"6798bfe5aa79035a3fa5091b","duration":105,"activityType":"exercise","userId":"1","activityTime":"morning","isHabit":false,"date":"2025-01-04T00:00:00.000Z","__v":0,"createdAt":"2025-01-28T11:30:45.105Z","updatedAt":"2025-01-28T11:30:45.105Z"},{"_id":"6798bfe5aa79035a3fa5091c","duration":88,"activityType":"reading","userId":"1","activityTime":"morning","isHabit":false,"date":"2024-12-05T00:00:00.000Z","__v":0,"createdAt":"2025-01-28T11:30:45.105Z","updatedAt":"2025-01-28T11:30:45.105Z"},{"_id":"6798bfe5aa79035a3fa5091d","duration":89,"activityType":"reading","userId":"1","activityTime":"evening","isHabit":false,"date":"2024-12-25T00:00:00.000Z","__v":0,"createdAt":"2025-01-28T11:30:45.105Z","updatedAt":"2025-01-28T11:30:45.105Z"},{"_id":"6798bfe5aa79035a3fa5091e","duration":180,"activityType":"cooking","userId":"1","activityTime":"all day","isHabit":false,"date":"2025-01-21T00:00:00.000Z","__v":0,"createdAt":"2025-01-28T11:30:45.105Z","updatedAt":"2025-01-28T11:30:45.105Z"},{"_id":"6798bfe5aa79035a3fa5091f","duration":154,"activityType":"friends","userId":"1","activityTime":"evening","isHabit":false,"date":"2025-01-04T00:00:00.000Z","__v":0,"createdAt":"2025-01-28T11:30:45.105Z","updatedAt":"2025-01-28T11:30:45.105Z"},{"_id":"6798bfe5aa79035a3fa50920","duration":67,"activityType":"cooking","userId":"1","activityTime":"afternoon","isHabit":false,"date":"2025-01-01T00:00:00.000Z","__v":0,"createdAt":"2025-01-28T11:30:45.105Z","updatedAt":"2025-01-28T11:30:45.105Z"},{"_id":"6798bfe5aa79035a3fa50921","duration":42,"activityType":"reading","userId":"1","activityTime":"all day","isHabit":false,"date":"2024-12-19T00:00:00.000Z","__v":0,"createdAt":"2025-01-28T11:30:45.105Z","updatedAt":"2025-01-28T11:30:45.105Z"},{"_id":"6798bfe5aa79035a3fa50922","duration":49,"activityType":"smoking","userId":"1","activityTime":"afternoon","isHabit":false,"date":"2025-01-07T00:00:00.000Z","__v":0,"createdAt":"2025-01-28T11:30:45.105Z","updatedAt":"2025-01-28T11:30:45.105Z"},{"_id":"6798bfe5aa79035a3fa50923","duration":103,"activityType":"party","userId":"1","activityTime":"all day","isHabit":false,"date":"2024-11-04T00:00:00.000Z","__v":0,"createdAt":"2025-01-28T11:30:45.105Z","updatedAt":"2025-01-28T11:30:45.105Z"},{"_id":"6798bfe5aa79035a3fa50924","duration":73,"activityType":"cooking","userId":"1","activityTime":"all day","isHabit":false,"date":"2024-12-26T00:00:00.000Z","__v":0,"createdAt":"2025-01-28T11:30:45.105Z","updatedAt":"2025-01-28T11:30:45.105Z"},{"_id":"6798bfe5aa79035a3fa50925","duration":23,"activityType":"smoking","userId":"1","activityTime":"all day","isHabit":false,"date":"2024-11-17T00:00:00.000Z","__v":0,"createdAt":"2025-01-28T11:30:45.105Z","updatedAt":"2025-01-28T11:30:45.105Z"},{"_id":"6798bfe5aa79035a3fa50926","duration":59,"activityType":"smoking","userId":"1","activityTime":"afternoon","isHabit":false,"date":"2024-11-23T00:00:00.000Z","__v":0,"createdAt":"2025-01-28T11:30:45.105Z","updatedAt":"2025-01-28T11:30:45.105Z"},{"_id":"6798bfe5aa79035a3fa50927","duration":47,"activityType":"meditation","userId":"1","activityTime":"all day","isHabit":false,"date":"2024-12-13T00:00:00.000Z","__v":0,"createdAt":"2025-01-28T11:30:45.105Z","updatedAt":"2025-01-28T11:30:45.105Z"},{"_id":"6798bfe5aa79035a3fa50928","duration":178,"activityType":"friends","userId":"1","activityTime":"morning","isHabit":false,"date":"2024-11-16T00:00:00.000Z","__v":0,"createdAt":"2025-01-28T11:30:45.105Z","updatedAt":"2025-01-28T11:30:45.105Z"},{"_id":"6798bfe5aa79035a3fa50929","duration":141,"activityType":"fast food","userId":"1","activityTime":"all day","isHabit":false,"date":"2025-01-07T00:00:00.000Z","__v":0,"createdAt":"2025-01-28T11:30:45.105Z","updatedAt":"2025-01-28T11:30:45.105Z"},{"_id":"6798bfe5aa79035a3fa5092a","duration":62,"activityType":"meditation","userId":"1","activityTime":"morning","isHabit":false,"date":"2025-01-13T00:00:00.000Z","__v":0,"createdAt":"2025-01-28T11:30:45.105Z","updatedAt":"2025-01-28T11:30:45.105Z"},{"_id":"6798bfe5aa79035a3fa5092b","duration":41,"activityType":"meditation","userId":"1","activityTime":"evening","isHabit":false,"date":"2024-12-21T00:00:00.000Z","__v":0,"createdAt":"2025-01-28T11:30:45.105Z","updatedAt":"2025-01-28T11:30:45.105Z"},{"_id":"6798bfe5aa79035a3fa5092c","duration":163,"activityType":"exercise","userId":"1","activityTime":"afternoon","isHabit":false,"date":"2024-12-20T00:00:00.000Z","__v":0,"createdAt":"2025-01-28T11:30:45.105Z","updatedAt":"2025-01-28T11:30:45.105Z"},{"_id":"6798bfe5aa79035a3fa5092d","duration":59,"activityType":"cleaning","userId":"1","activityTime":"morning","isHabit":false,"date":"2025-01-09T00:00:00.000Z","__v":0,"createdAt":"2025-01-28T11:30:45.105Z","updatedAt":"2025-01-28T11:30:45.105Z"},{"_id":"6798bfe5aa79035a3fa5092e","duration":173,"activityType":"cleaning","userId":"1","activityTime":"morning","isHabit":false,"date":"2024-12-20T00:00:00.000Z","__v":0,"createdAt":"2025-01-28T11:30:45.105Z","updatedAt":"2025-01-28T11:30:45.105Z"},{"_id":"6798bfe5aa79035a3fa5092f","duration":100,"activityType":"shopping","userId":"1","activityTime":"afternoon","isHabit":false,"date":"2024-12-14T00:00:00.000Z","__v":0,"createdAt":"2025-01-28T11:30:45.105Z","updatedAt":"2025-01-28T11:30:45.105Z"},{"_id":"6798bfe5aa79035a3fa50930","duration":67,"activityType":"gaming","userId":"1","activityTime":"afternoon","isHabit":false,"date":"2024-12-02T00:00:00.000Z","__v":0,"createdAt":"2025-01-28T11:30:45.105Z","updatedAt":"2025-01-28T11:30:45.105Z"},{"_id":"6798bfe5aa79035a3fa50931","duration":140,"activityType":"exercise","userId":"1","activityTime":"evening","isHabit":false,"date":"2024-12-10T00:00:00.000Z","__v":0,"createdAt":"2025-01-28T11:30:45.105Z","updatedAt":"2025-01-28T11:30:45.105Z"},{"_id":"6798bfe5aa79035a3fa50932","duration":69,"activityType":"gaming","userId":"1","activityTime":"evening","isHabit":false,"date":"2024-12-16T00:00:00.000Z","__v":0,"createdAt":"2025-01-28T11:30:45.105Z","updatedAt":"2025-01-28T11:30:45.105Z"},{"_id":"6798bfe5aa79035a3fa50933","duration":78,"activityType":"fast food","userId":"1","activityTime":"evening","isHabit":false,"date":"2024-12-04T00:00:00.000Z","__v":0,"createdAt":"2025-01-28T11:30:45.105Z","updatedAt":"2025-01-28T11:30:45.105Z"},{"_id":"6798bfe5aa79035a3fa50934","duration":72,"activityType":"gaming","userId":"1","activityTime":"morning","isHabit":false,"date":"2024-12-04T00:00:00.000Z","__v":0,"createdAt":"2025-01-28T11:30:45.105Z","updatedAt":"2025-01-28T11:30:45.105Z"},{"_id":"6798bfe5aa79035a3fa50935","duration":11,"activityType":"meditation","userId":"1","activityTime":"evening","isHabit":false,"date":"2024-12-26T00:00:00.000Z","__v":0,"createdAt":"2025-01-28T11:30:45.106Z","updatedAt":"2025-01-28T11:30:45.106Z"},{"_id":"6798bfe5aa79035a3fa50936","duration":21,"activityType":"party","userId":"1","activityTime":"afternoon","isHabit":false,"date":"2024-11-18T00:00:00.000Z","__v":0,"createdAt":"2025-01-28T11:30:45.106Z","updatedAt":"2025-01-28T11:30:45.106Z"},{"_id":"6798bfe5aa79035a3fa50937","duration":96,"activityType":"meditation","userId":"1","activityTime":"all day","isHabit":false,"date":"2024-12-18T00:00:00.000Z","__v":0,"createdAt":"2025-01-28T11:30:45.106Z","updatedAt":"2025-01-28T11:30:45.106Z"},{"_id":"6798bfe5aa79035a3fa50938","duration":11,"activityType":"cooking","userId":"1","activityTime":"evening","isHabit":false,"date":"2025-01-22T00:00:00.000Z","__v":0,"createdAt":"2025-01-28T11:30:45.106Z","updatedAt":"2025-01-28T11:30:45.106Z"},{"_id":"6798bfe5aa79035a3fa50939","duration":56,"activityType":"gaming","userId":"1","activityTime":"all day","isHabit":false,"date":"2025-01-01T00:00:00.000Z","__v":0,"createdAt":"2025-01-28T11:30:45.106Z","updatedAt":"2025-01-28T11:30:45.106Z"},{"_id":"6798bfe5aa79035a3fa5093a","duration":159,"activityType":"exercise","userId":"1","activityTime":"morning","isHabit":false,"date":"2025-01-14T00:00:00.000Z","__v":0,"createdAt":"2025-01-28T11:30:45.106Z","updatedAt":"2025-01-28T11:30:45.106Z"},{"_id":"6798bfe5aa79035a3fa5093b","duration":103,"activityType":"meditation","userId":"1","activityTime":"evening","isHabit":false,"date":"2024-12-20T00:00:00.000Z","__v":0,"createdAt":"2025-01-28T11:30:45.106Z","updatedAt":"2025-01-28T11:30:45.106Z"},{"_id":"6798bfe5aa79035a3fa5093c","duration":89,"activityType":"screen time","userId":"1","activityTime":"evening","isHabit":false,"date":"2024-12-18T00:00:00.000Z","__v":0,"createdAt":"2025-01-28T11:30:45.106Z","updatedAt":"2025-01-28T11:30:45.106Z"},{"_id":"6798bfe5aa79035a3fa5093d","duration":56,"activityType":"friends","userId":"1","activityTime":"all day","isHabit":false,"date":"2025-01-13T00:00:00.000Z","__v":0,"createdAt":"2025-01-28T11:30:45.106Z","updatedAt":"2025-01-28T11:30:45.106Z"},{"_id":"6798bfe5aa79035a3fa5093e","duration":139,"activityType":"gaming","userId":"1","activityTime":"morning","isHabit":false,"date":"2024-12-26T00:00:00.000Z","__v":0,"createdAt":"2025-01-28T11:30:45.106Z","updatedAt":"2025-01-28T11:30:45.106Z"},{"_id":"6798bfe5aa79035a3fa5093f","duration":64,"activityType":"smoking","userId":"1","activityTime":"afternoon","isHabit":false,"date":"2024-12-29T00:00:00.000Z","__v":0,"createdAt":"2025-01-28T11:30:45.106Z","updatedAt":"2025-01-28T11:30:45.106Z"},{"_id":"6798bfe5aa79035a3fa50940","duration":164,"activityType":"gaming","userId":"1","activityTime":"evening","isHabit":false,"date":"2025-01-18T00:00:00.000Z","__v":0,"createdAt":"2025-01-28T11:30:45.106Z","updatedAt":"2025-01-28T11:30:45.106Z"},{"_id":"6798bfe5aa79035a3fa50941","duration":107,"activityType":"meditation","userId":"1","activityTime":"morning","isHabit":false,"date":"2024-12-21T00:00:00.000Z","__v":0,"createdAt":"2025-01-28T11:30:45.106Z","updatedAt":"2025-01-28T11:30:45.106Z"},{"_id":"6798bfe5aa79035a3fa50942","duration":48,"activityType":"shopping","userId":"1","activityTime":"all day","isHabit":false,"date":"2025-01-14T00:00:00.000Z","__v":0,"createdAt":"2025-01-28T11:30:45.106Z","updatedAt":"2025-01-28T11:30:45.106Z"},{"_id":"6798bfe5aa79035a3fa50943","duration":36,"activityType":"meditation","userId":"1","activityTime":"all day","isHabit":false,"date":"2024-12-31T00:00:00.000Z","__v":0,"createdAt":"2025-01-28T11:30:45.106Z","updatedAt":"2025-01-28T11:30:45.106Z"},{"_id":"6798bfe5aa79035a3fa50944","duration":147,"activityType":"screen time","userId":"1","activityTime":"all day","isHabit":false,"date":"2024-11-03T00:00:00.000Z","__v":0,"createdAt":"2025-01-28T11:30:45.106Z","updatedAt":"2025-01-28T11:30:45.106Z"},{"_id":"6798bfe5aa79035a3fa50945","duration":134,"activityType":"shopping","userId":"1","activityTime":"all day","isHabit":false,"date":"2024-11-17T00:00:00.000Z","__v":0,"createdAt":"2025-01-28T11:30:45.106Z","updatedAt":"2025-01-28T11:30:45.106Z"},{"_id":"6798bfe5aa79035a3fa50946","duration":111,"activityType":"shopping","userId":"1","activityTime":"morning","isHabit":false,"date":"2024-11-23T00:00:00.000Z","__v":0,"createdAt":"2025-01-28T11:30:45.106Z","updatedAt":"2025-01-28T11:30:45.106Z"},{"_id":"6798bfe5aa79035a3fa50947","duration":144,"activityType":"gaming","userId":"1","activityTime":"evening","isHabit":false,"date":"2024-10-30T00:00:00.000Z","__v":0,"createdAt":"2025-01-28T11:30:45.106Z","updatedAt":"2025-01-28T11:30:45.106Z"},{"_id":"6798bfe5aa79035a3fa50948","duration":141,"activityType":"cooking","userId":"1","activityTime":"morning","isHabit":false,"date":"2024-11-02T00:00:00.000Z","__v":0,"createdAt":"2025-01-28T11:30:45.106Z","updatedAt":"2025-01-28T11:30:45.106Z"},{"_id":"6798bfe5aa79035a3fa50949","duration":136,"activityType":"meditation","userId":"1","activityTime":"evening","isHabit":false,"date":"2024-11-16T00:00:00.000Z","__v":0,"createdAt":"2025-01-28T11:30:45.106Z","updatedAt":"2025-01-28T11:30:45.106Z"},{"_id":"6798bfe5aa79035a3fa5094a","duration":138,"activityType":"shopping","userId":"1","activityTime":"evening","isHabit":false,"date":"2025-01-07T00:00:00.000Z","__v":0,"createdAt":"2025-01-28T11:30:45.106Z","updatedAt":"2025-01-28T11:30:45.106Z"},{"_id":"6798bfe5aa79035a3fa5094b","duration":90,"activityType":"reading","userId":"1","activityTime":"all day","isHabit":false,"date":"2024-12-31T00:00:00.000Z","__v":0,"createdAt":"2025-01-28T11:30:45.106Z","updatedAt":"2025-01-28T11:30:45.106Z"},{"_id":"6798bfe5aa79035a3fa5094c","duration":98,"activityType":"friends","userId":"1","activityTime":"all day","isHabit":false,"date":"2024-11-02T00:00:00.000Z","__v":0,"createdAt":"2025-01-28T11:30:45.106Z","updatedAt":"2025-01-28T11:30:45.106Z"},{"_id":"6798bfe5aa79035a3fa5094d","duration":103,"activityType":"smoking","userId":"1","activityTime":"afternoon","isHabit":false,"date":"2025-01-13T00:00:00.000Z","__v":0,"createdAt":"2025-01-28T11:30:45.106Z","updatedAt":"2025-01-28T11:30:45.106Z"},{"_id":"6798bfe5aa79035a3fa5094e","duration":81,"activityType":"exercise","userId":"1","activityTime":"afternoon","isHabit":false,"date":"2024-11-12T00:00:00.000Z","__v":0,"createdAt":"2025-01-28T11:30:45.106Z","updatedAt":"2025-01-28T11:30:45.106Z"},{"_id":"6798bfe5aa79035a3fa5094f","duration":40,"activityType":"friends","userId":"1","activityTime":"morning","isHabit":false,"date":"2024-11-05T00:00:00.000Z","__v":0,"createdAt":"2025-01-28T11:30:45.106Z","updatedAt":"2025-01-28T11:30:45.106Z"},{"_id":"6798bfe5aa79035a3fa50950","duration":175,"activityType":"meditation","userId":"1","activityTime":"morning","isHabit":false,"date":"2024-12-17T00:00:00.000Z","__v":0,"createdAt":"2025-01-28T11:30:45.106Z","updatedAt":"2025-01-28T11:30:45.106Z"},{"_id":"6798bfe5aa79035a3fa50951","duration":85,"activityType":"smoking","userId":"1","activityTime":"morning","isHabit":false,"date":"2024-12-27T00:00:00.000Z","__v":0,"createdAt":"2025-01-28T11:30:45.106Z","updatedAt":"2025-01-28T11:30:45.106Z"},{"_id":"6798bfe5aa79035a3fa50952","duration":63,"activityType":"meditation","userId":"1","activityTime":"morning","isHabit":false,"date":"2025-01-11T00:00:00.000Z","__v":0,"createdAt":"2025-01-28T11:30:45.106Z","updatedAt":"2025-01-28T11:30:45.106Z"},{"_id":"6798bfe5aa79035a3fa50953","duration":109,"activityType":"screen time","userId":"1","activityTime":"all day","isHabit":false,"date":"2024-11-05T00:00:00.000Z","__v":0,"createdAt":"2025-01-28T11:30:45.106Z","updatedAt":"2025-01-28T11:30:45.106Z"},{"_id":"6798bfe5aa79035a3fa50954","duration":54,"activityType":"party","userId":"1","activityTime":"morning","isHabit":false,"date":"2025-01-08T00:00:00.000Z","__v":0,"createdAt":"2025-01-28T11:30:45.106Z","updatedAt":"2025-01-28T11:30:45.106Z"},{"_id":"6798bfe5aa79035a3fa50955","duration":62,"activityType":"cooking","userId":"1","activityTime":"morning","isHabit":false,"date":"2024-12-15T00:00:00.000Z","__v":0,"createdAt":"2025-01-28T11:30:45.106Z","updatedAt":"2025-01-28T11:30:45.106Z"},{"_id":"6798bfe5aa79035a3fa50956","duration":62,"activityType":"cleaning","userId":"1","activityTime":"afternoon","isHabit":false,"date":"2025-01-10T00:00:00.000Z","__v":0,"createdAt":"2025-01-28T11:30:45.106Z","updatedAt":"2025-01-28T11:30:45.106Z"},{"_id":"6798bfe5aa79035a3fa50957","duration":136,"activityType":"fast food","userId":"1","activityTime":"morning","isHabit":false,"date":"2025-01-25T00:00:00.000Z","__v":0,"createdAt":"2025-01-28T11:30:45.106Z","updatedAt":"2025-01-28T11:30:45.106Z"},{"_id":"6798bfe5aa79035a3fa50958","duration":16,"activityType":"screen time","userId":"1","activityTime":"morning","isHabit":false,"date":"2024-12-19T00:00:00.000Z","__v":0,"createdAt":"2025-01-28T11:30:45.106Z","updatedAt":"2025-01-28T11:30:45.106Z"},{"_id":"6798bfe5aa79035a3fa50959","duration":60,"activityType":"gaming","userId":"1","activityTime":"all day","isHabit":false,"date":"2024-12-13T00:00:00.000Z","__v":0,"createdAt":"2025-01-28T11:30:45.106Z","updatedAt":"2025-01-28T11:30:45.106Z"},{"_id":"6798bfe5aa79035a3fa5095a","duration":142,"activityType":"exercise","userId":"1","activityTime":"all day","isHabit":false,"date":"2025-01-13T00:00:00.000Z","__v":0,"createdAt":"2025-01-28T11:30:45.106Z","updatedAt":"2025-01-28T11:30:45.106Z"},{"_id":"6798bfe5aa79035a3fa5095b","duration":70,"activityType":"meditation","userId":"1","activityTime":"all day","isHabit":false,"date":"2024-12-20T00:00:00.000Z","__v":0,"createdAt":"2025-01-28T11:30:45.106Z","updatedAt":"2025-01-28T11:30:45.106Z"},{"_id":"6798bfe5aa79035a3fa5095c","duration":132,"activityType":"cleaning","userId":"1","activityTime":"all day","isHabit":false,"date":"2024-10-31T00:00:00.000Z","__v":0,"createdAt":"2025-01-28T11:30:45.106Z","updatedAt":"2025-01-28T11:30:45.106Z"},{"_id":"6798bfe5aa79035a3fa5095d","duration":172,"activityType":"gaming","userId":"1","activityTime":"all day","isHabit":false,"date":"2024-11-19T00:00:00.000Z","__v":0,"createdAt":"2025-01-28T11:30:45.106Z","updatedAt":"2025-01-28T11:30:45.106Z"},{"_id":"6798bfe5aa79035a3fa5095e","duration":26,"activityType":"cooking","userId":"1","activityTime":"evening","isHabit":false,"date":"2024-12-13T00:00:00.000Z","__v":0,"createdAt":"2025-01-28T11:30:45.106Z","updatedAt":"2025-01-28T11:30:45.106Z"},{"_id":"6798bfe5aa79035a3fa5095f","duration":45,"activityType":"overtime","userId":"1","activityTime":"morning","isHabit":false,"date":"2024-11-15T00:00:00.000Z","__v":0,"createdAt":"2025-01-28T11:30:45.106Z","updatedAt":"2025-01-28T11:30:45.106Z"},{"_id":"6798bfe5aa79035a3fa50960","duration":120,"activityType":"gaming","userId":"1","activityTime":"morning","isHabit":false,"date":"2024-11-19T00:00:00.000Z","__v":0,"createdAt":"2025-01-28T11:30:45.106Z","updatedAt":"2025-01-28T11:30:45.106Z"},{"_id":"6798bfe5aa79035a3fa50961","duration":108,"activityType":"reading","userId":"1","activityTime":"evening","isHabit":false,"date":"2024-11-14T00:00:00.000Z","__v":0,"createdAt":"2025-01-28T11:30:45.106Z","updatedAt":"2025-01-28T11:30:45.106Z"},{"_id":"6798bfe5aa79035a3fa50962","duration":61,"activityType":"cleaning","userId":"1","activityTime":"morning","isHabit":false,"date":"2025-01-26T00:00:00.000Z","__v":0,"createdAt":"2025-01-28T11:30:45.106Z","updatedAt":"2025-01-28T11:30:45.106Z"},{"_id":"6798bfe5aa79035a3fa50963","duration":151,"activityType":"smoking","userId":"1","activityTime":"morning","isHabit":false,"date":"2024-12-02T00:00:00.000Z","__v":0,"createdAt":"2025-01-28T11:30:45.106Z","updatedAt":"2025-01-28T11:30:45.106Z"},{"_id":"6798bfe5aa79035a3fa50964","duration":52,"activityType":"friends","userId":"1","activityTime":"afternoon","isHabit":false,"date":"2024-12-18T00:00:00.000Z","__v":0,"createdAt":"2025-01-28T11:30:45.106Z","updatedAt":"2025-01-28T11:30:45.106Z"},{"_id":"6798bfe5aa79035a3fa50965","duration":92,"activityType":"fast food","userId":"1","activityTime":"all day","isHabit":false,"date":"2024-11-01T00:00:00.000Z","__v":0,"createdAt":"2025-01-28T11:30:45.106Z","updatedAt":"2025-01-28T11:30:45.106Z"},{"_id":"6798bfe5aa79035a3fa50966","duration":51,"activityType":"exercise","userId":"1","activityTime":"morning","isHabit":false,"date":"2024-12-20T00:00:00.000Z","__v":0,"createdAt":"2025-01-28T11:30:45.106Z","updatedAt":"2025-01-28T11:30:45.106Z"},{"_id":"6798bfe5aa79035a3fa50967","duration":62,"activityType":"party","userId":"1","activityTime":"all day","isHabit":false,"date":"2025-01-01T00:00:00.000Z","__v":0,"createdAt":"2025-01-28T11:30:45.106Z","updatedAt":"2025-01-28T11:30:45.106Z"},{"_id":"6798bfe5aa79035a3fa50968","duration":44,"activityType":"overtime","userId":"1","activityTime":"evening","isHabit":false,"date":"2024-12-30T00:00:00.000Z","__v":0,"createdAt":"2025-01-28T11:30:45.106Z","updatedAt":"2025-01-28T11:30:45.106Z"},{"_id":"6798bfe5aa79035a3fa50969","duration":39,"activityType":"shopping","userId":"1","activityTime":"morning","isHabit":false,"date":"2024-12-19T00:00:00.000Z","__v":0,"createdAt":"2025-01-28T11:30:45.106Z","updatedAt":"2025-01-28T11:30:45.106Z"},{"_id":"6798bfe5aa79035a3fa5096a","duration":65,"activityType":"screen time","userId":"1","activityTime":"all day","isHabit":false,"date":"2024-12-21T00:00:00.000Z","__v":0,"createdAt":"2025-01-28T11:30:45.106Z","updatedAt":"2025-01-28T11:30:45.106Z"},{"_id":"6798bfe5aa79035a3fa5096b","duration":69,"activityType":"exercise","userId":"1","activityTime":"evening","isHabit":false,"date":"2024-11-28T00:00:00.000Z","__v":0,"createdAt":"2025-01-28T11:30:45.106Z","updatedAt":"2025-01-28T11:30:45.106Z"},{"_id":"6798bfe5aa79035a3fa5096c","duration":86,"activityType":"gaming","userId":"1","activityTime":"afternoon","isHabit":false,"date":"2024-11-10T00:00:00.000Z","__v":0,"createdAt":"2025-01-28T11:30:45.106Z","updatedAt":"2025-01-28T11:30:45.106Z"},{"_id":"6798bfe5aa79035a3fa5096d","duration":155,"activityType":"party","userId":"1","activityTime":"afternoon","isHabit":false,"date":"2024-12-01T00:00:00.000Z","__v":0,"createdAt":"2025-01-28T11:30:45.106Z","updatedAt":"2025-01-28T11:30:45.106Z"},{"_id":"6798bfe5aa79035a3fa5096e","duration":143,"activityType":"meditation","userId":"1","activityTime":"evening","isHabit":false,"date":"2024-12-28T00:00:00.000Z","__v":0,"createdAt":"2025-01-28T11:30:45.106Z","updatedAt":"2025-01-28T11:30:45.106Z"},{"_id":"6798bfe5aa79035a3fa5096f","duration":53,"activityType":"cleaning","userId":"1","activityTime":"morning","isHabit":false,"date":"2024-12-17T00:00:00.000Z","__v":0,"createdAt":"2025-01-28T11:30:45.106Z","updatedAt":"2025-01-28T11:30:45.106Z"},{"_id":"6798bfe5aa79035a3fa50970","duration":133,"activityType":"overtime","userId":"1","activityTime":"morning","isHabit":false,"date":"2025-01-07T00:00:00.000Z","__v":0,"createdAt":"2025-01-28T11:30:45.106Z","updatedAt":"2025-01-28T11:30:45.106Z"},{"_id":"6798bfe5aa79035a3fa50971","duration":111,"activityType":"screen time","userId":"1","activityTime":"afternoon","isHabit":false,"date":"2025-01-15T00:00:00.000Z","__v":0,"createdAt":"2025-01-28T11:30:45.106Z","updatedAt":"2025-01-28T11:30:45.106Z"},{"_id":"6798bfe5aa79035a3fa50972","duration":173,"activityType":"cleaning","userId":"1","activityTime":"evening","isHabit":false,"date":"2024-11-14T00:00:00.000Z","__v":0,"createdAt":"2025-01-28T11:30:45.106Z","updatedAt":"2025-01-28T11:30:45.106Z"},{"_id":"6798bfe5aa79035a3fa50973","duration":65,"activityType":"friends","userId":"1","activityTime":"afternoon","isHabit":false,"date":"2025-01-25T00:00:00.000Z","__v":0,"createdAt":"2025-01-28T11:30:45.106Z","updatedAt":"2025-01-28T11:30:45.106Z"},{"_id":"6798bfe5aa79035a3fa50974","duration":72,"activityType":"gaming","userId":"1","activityTime":"morning","isHabit":false,"date":"2024-12-29T00:00:00.000Z","__v":0,"createdAt":"2025-01-28T11:30:45.106Z","updatedAt":"2025-01-28T11:30:45.106Z"},{"_id":"6798bfe5aa79035a3fa50975","duration":65,"activityType":"gaming","userId":"1","activityTime":"morning","isHabit":false,"date":"2025-01-22T00:00:00.000Z","__v":0,"createdAt":"2025-01-28T11:30:45.106Z","updatedAt":"2025-01-28T11:30:45.106Z"},{"_id":"6798bfe5aa79035a3fa50976","duration":59,"activityType":"shopping","userId":"1","activityTime":"all day","isHabit":false,"date":"2024-11-06T00:00:00.000Z","__v":0,"createdAt":"2025-01-28T11:30:45.106Z","updatedAt":"2025-01-28T11:30:45.106Z"},{"_id":"6798bfe5aa79035a3fa50977","duration":160,"activityType":"reading","userId":"1","activityTime":"all day","isHabit":false,"date":"2024-11-06T00:00:00.000Z","__v":0,"createdAt":"2025-01-28T11:30:45.106Z","updatedAt":"2025-01-28T11:30:45.106Z"},{"_id":"6798bfe5aa79035a3fa50978","duration":20,"activityType":"reading","userId":"1","activityTime":"evening","isHabit":false,"date":"2024-11-10T00:00:00.000Z","__v":0,"createdAt":"2025-01-28T11:30:45.106Z","updatedAt":"2025-01-28T11:30:45.106Z"},{"_id":"6798bfe5aa79035a3fa50979","duration":102,"activityType":"meditation","userId":"1","activityTime":"afternoon","isHabit":false,"date":"2024-12-03T00:00:00.000Z","__v":0,"createdAt":"2025-01-28T11:30:45.106Z","updatedAt":"2025-01-28T11:30:45.106Z"},{"_id":"6798bfe5aa79035a3fa5097a","duration":38,"activityType":"smoking","userId":"1","activityTime":"morning","isHabit":false,"date":"2024-11-02T00:00:00.000Z","__v":0,"createdAt":"2025-01-28T11:30:45.106Z","updatedAt":"2025-01-28T11:30:45.106Z"},{"_id":"6798bfe5aa79035a3fa5097b","duration":27,"activityType":"overtime","userId":"1","activityTime":"evening","isHabit":false,"date":"2025-01-08T00:00:00.000Z","__v":0,"createdAt":"2025-01-28T11:30:45.106Z","updatedAt":"2025-01-28T11:30:45.106Z"},{"_id":"6798bfe5aa79035a3fa5097c","duration":108,"activityType":"shopping","userId":"1","activityTime":"afternoon","isHabit":false,"date":"2024-12-06T00:00:00.000Z","__v":0,"createdAt":"2025-01-28T11:30:45.106Z","updatedAt":"2025-01-28T11:30:45.106Z"},{"_id":"6798bfe5aa79035a3fa5097d","duration":150,"activityType":"friends","userId":"1","activityTime":"all day","isHabit":false,"date":"2025-01-02T00:00:00.000Z","__v":0,"createdAt":"2025-01-28T11:30:45.106Z","updatedAt":"2025-01-28T11:30:45.106Z"},{"_id":"6798bfe5aa79035a3fa5097e","duration":26,"activityType":"shopping","userId":"1","activityTime":"all day","isHabit":false,"date":"2024-12-08T00:00:00.000Z","__v":0,"createdAt":"2025-01-28T11:30:45.106Z","updatedAt":"2025-01-28T11:30:45.106Z"},{"_id":"6798bfe5aa79035a3fa5097f","duration":93,"activityType":"party","userId":"1","activityTime":"all day","isHabit":false,"date":"2024-11-07T00:00:00.000Z","__v":0,"createdAt":"2025-01-28T11:30:45.106Z","updatedAt":"2025-01-28T11:30:45.106Z"},{"_id":"6798bfe5aa79035a3fa50980","duration":144,"activityType":"friends","userId":"1","activityTime":"morning","isHabit":false,"date":"2025-01-09T00:00:00.000Z","__v":0,"createdAt":"2025-01-28T11:30:45.106Z","updatedAt":"2025-01-28T11:30:45.106Z"},{"_id":"6798bfe5aa79035a3fa50981","duration":97,"activityType":"reading","userId":"1","activityTime":"morning","isHabit":false,"date":"2024-11-21T00:00:00.000Z","__v":0,"createdAt":"2025-01-28T11:30:45.106Z","updatedAt":"2025-01-28T11:30:45.106Z"},{"_id":"6798bfe5aa79035a3fa50982","duration":65,"activityType":"party","userId":"1","activityTime":"all day","isHabit":false,"date":"2024-11-23T00:00:00.000Z","__v":0,"createdAt":"2025-01-28T11:30:45.106Z","updatedAt":"2025-01-28T11:30:45.106Z"},{"_id":"6798bfe5aa79035a3fa50983","duration":114,"activityType":"smoking","userId":"1","activityTime":"evening","isHabit":false,"date":"2024-11-21T00:00:00.000Z","__v":0,"createdAt":"2025-01-28T11:30:45.106Z","updatedAt":"2025-01-28T11:30:45.106Z"},{"_id":"6798bfe5aa79035a3fa50984","duration":115,"activityType":"smoking","userId":"1","activityTime":"evening","isHabit":false,"date":"2024-12-24T00:00:00.000Z","__v":0,"createdAt":"2025-01-28T11:30:45.106Z","updatedAt":"2025-01-28T11:30:45.106Z"},{"_id":"6798bfe5aa79035a3fa50985","duration":23,"activityType":"reading","userId":"1","activityTime":"evening","isHabit":false,"date":"2024-12-26T00:00:00.000Z","__v":0,"createdAt":"2025-01-28T11:30:45.106Z","updatedAt":"2025-01-28T11:30:45.106Z"},{"_id":"6798f29b085252ac7140f526","duration":33,"activityType":"cooking","userId":"1","activityTime":"morning","isHabit":false,"date":"2025-01-28T14:57:03.178Z","createdAt":"2025-01-28T15:07:07.922Z","updatedAt":"2025-01-28T15:07:07.922Z","__v":0},{"_id":"679904c8429434b19b9a20cf","duration":116,"activityType":"cooking","userId":"1","activityTime":"afternoon","isHabit":false,"date":"2025-01-28T16:16:44.684Z","createdAt":"2025-01-28T16:24:40.982Z","updatedAt":"2025-01-28T16:24:40.982Z","__v":0}]